{
  "$schema": "https://mintlify.com/docs.json",
  "name": "Pika Skills",
  "theme": "luma",
  "colors": {
    "primary": "#040404",
    "light": "#ffffff",
    "dark": "#040404"
  },
  "favicon": "https://icons.duckduckgo.com/ip3/pika.me.ico",
  "logo": {
    "light": "https://media.brand.dev/d0cdee2b-a0b0-4968-8560-f90800849213.svg",
    "dark": "https://media.brand.dev/d0cdee2b-a0b0-4968-8560-f90800849213.svg"
  },
  "navbar": {
    "primary": {
      "type": "github",
      "href": "https://github.com/Pika-Labs/Pika-Skills"
    }
  },
  "footer": {
    "socials": {
      "github": "https://github.com/Pika-Labs/Pika-Skills"
    }
  },
  "navigation": {
    "groups": [
      {
        "group": "Get Started",
        "pages": [
          "introduction",
          "quickstart"
        ]
      },
      {
        "group": "Skills",
        "pages": [
          "skills/overview",
          "skills/pikastream-video-meeting"
        ]
      },
      {
        "group": "Reference",
        "pages": [
          "reference/commands",
          "reference/environment-variables",
          "reference/exit-codes",
          "reference/contributing"
        ]
      }
    ]
  }
}
